streamdeck_sdk_pi/__init__.py
streamdeck_sdk_pi/property_inspector/__init__.py
streamdeck_sdk_pi/property_inspector/property_inspector.py
streamdeck_sdk_pi/property_inspector/objs/__init__.py
streamdeck_sdk_pi/property_inspector/objs/base.py
streamdeck_sdk_pi/property_inspector/objs/checkbox.py
streamdeck_sdk_pi/property_inspector/objs/color.py
streamdeck_sdk_pi/property_inspector/objs/date_obj.py
streamdeck_sdk_pi/property_inspector/objs/datetime_local.py
streamdeck_sdk_pi/property_inspector/objs/details.py
streamdeck_sdk_pi/property_inspector/objs/file.py
streamdeck_sdk_pi/property_inspector/objs/group.py
streamdeck_sdk_pi/property_inspector/objs/heading.py
streamdeck_sdk_pi/property_inspector/objs/line.py
streamdeck_sdk_pi/property_inspector/objs/message.py
streamdeck_sdk_pi/property_inspector/objs/meter.py
streamdeck_sdk_pi/property_inspector/objs/month.py
streamdeck_sdk_pi/property_inspector/objs/password.py
streamdeck_sdk_pi/property_inspector/objs/progress.py
streamdeck_sdk_pi/property_inspector/objs/radio.py
streamdeck_sdk_pi/property_inspector/objs/range.py
streamdeck_sdk_pi/property_inspector/objs/select.py
streamdeck_sdk_pi/property_inspector/objs/textarea.py
streamdeck_sdk_pi/property_inspector/objs/textfield.py
streamdeck_sdk_pi/property_inspector/objs/time_obj.py
streamdeck_sdk_pi/property_inspector/objs/week.py
streamdeck_sdk_pi-0.0.1.dist-info/LICENSE
streamdeck_sdk_pi-0.0.1.dist-info/METADATA
streamdeck_sdk_pi-0.0.1.dist-info/WHEEL
streamdeck_sdk_pi-0.0.1.dist-info/top_level.txt
streamdeck_sdk_pi-0.0.1.dist-info/RECORD
