Metadata-Version: 2.1
Name: streamdeck_sdk_pi
Version: 0.0.1
Summary: Library for creating Stream Deck Property Inspector in Python.
Author-email: Grigoriy Gusev <thegrigus@gmail.com>
Project-URL: Homepage, https://github.com/gri-gus/streamdeck-python-sdk-pi
Project-URL: Source, https://github.com/gri-gus/streamdeck-python-sdk-pi
Keywords: property inspector,property inspector generator,streamdeck property inspector generator,streamdeck property inspector,streamdeck pi,python,sdk,streamdeck,streamdeck-sdk,streamdeck_sdk,stream deck sdk,stream deck,elgato,elgato sdk,elgato stream deck,streamdeck-python-sdk,streamdeck_python_sdk,streamdeck python sdk
Classifier: Programming Language :: Python :: 3.10
Classifier: License :: OSI Approved :: Apache Software License
Classifier: Operating System :: OS Independent
Requires-Python: >=3.8
License-File: LICENSE
